paatch.py
paatch-1.20.3.dist-info/licenses/LICENSE
paatch-1.20.3.dist-info/METADATA
paatch-1.20.3.dist-info/WHEEL
paatch-1.20.3.dist-info/entry_points.txt
paatch-1.20.3.dist-info/top_level.txt
paatch-1.20.3.dist-info/RECORD
