Metadata-Version: 2.4
Name: paatch
Version: 1.20.3
Summary: Library to parse and apply unified diffs.
Home-page: https://github.com/timfel/paatch
Author: Tim Felgentreff
Author-email: timfelgentreff@gmail.com
License: UPL
Keywords: patch,parse,diff,strip,diffstat
Classifier: Development Status :: 5 - Production/Stable
Classifier: Intended Audience :: Developers
Classifier: Topic :: Software Development :: Build Tools
Classifier: Programming Language :: Python :: 3
Classifier: Programming Language :: Python :: 3.10
Classifier: Programming Language :: Python :: 3.11
Classifier: Programming Language :: Python :: 3.12
Classifier: Programming Language :: Python :: 3.13
Requires-Python: >=3.10
License-File: LICENSE
Dynamic: author
Dynamic: author-email
Dynamic: classifier
Dynamic: description
Dynamic: description-content-type
Dynamic: home-page
Dynamic: keywords
Dynamic: license
Dynamic: license-file
Dynamic: requires-python
Dynamic: summary
